README.md
pyproject.toml
ommx_python_mip_adapter/__init__.py
ommx_python_mip_adapter/adapter.py
ommx_python_mip_adapter/exception.py
ommx_python_mip_adapter/python_mip_to_ommx.py
ommx_python_mip_adapter.egg-info/PKG-INFO
ommx_python_mip_adapter.egg-info/SOURCES.txt
ommx_python_mip_adapter.egg-info/dependency_links.txt
ommx_python_mip_adapter.egg-info/requires.txt
ommx_python_mip_adapter.egg-info/top_level.txt
tests/test_adapter.py
tests/test_constant_constraint.py
tests/test_integration.py
tests/test_model_to_instance.py